{"name":{"US-en":"Barold","EU-en":"Barold","EU-de":"Hubert","EU-es":"Plácido","US-es":"Plácido","EU-fr":"Manu","US-fr":"Manu","EU-it":"Placido","EU-nl":"Barold","CN-zh":"阿西","TW-zh":"阿西","JP-ja":"ニッシー","KR-ko":"곰시","EU-ru":"Барольд"},"personality":"Lazy","birthday":"March 2nd","birthdate":"2/3","species":"Cub","gender":"Male","subtype":"A","hobby":"Play","icon":"https://acnhapi.com/v1/icons/villagers/78","image":"https://acnhapi.com/v1/images/villagers/78","bubbleColor":"#bfbfbf","textColor":"#5e5e5e","saying":"Please DO feed the bears!","catchPhrase":{"US-en":"cubby","EU-en":"cubby","EU-de":"mwuuu","EU-es":"apurri","US-es":"apurri","EU-fr":"dodododu","US-fr":"dodododu","EU-it":"babalù","EU-nl":"welpje","CN-zh":"算了","TW-zh":"算了","JP-ja":"いっそ","KR-ko":"아니그냥","EU-ru":"берлога"},"description":"Barold is a cub villager in the Animal Crossing series. He first appeared in Animal Crossing: New Leaf. His name is a pun on \"bear\" and a common name, \"Harold\"."}