{"name":{"US-en":"Piper","EU-en":"Piper","EU-de":"Iris","EU-es":"Bárbara","US-es":"Bárbara","EU-fr":"Neige","US-fr":"Neige","EU-it":"Giuliva","EU-nl":"Piper","CN-zh":"丽婷","TW-zh":"麗婷","JP-ja":"レイコ","KR-ko":"파이프","EU-ru":"Пайпер"},"personality":"Peppy","birthday":"April 18th","birthdate":"18/4","species":"Bird","gender":"Female","subtype":"A","hobby":"Play","icon":"https://acnhapi.com/v1/icons/villagers/28","image":"https://acnhapi.com/v1/images/villagers/28","bubbleColor":"#ffffff","textColor":"#848484","saying":"Where there's life, there's hope.","catchPhrase":{"US-en":"chickadee","EU-en":"chickadee","EU-de":"tschikadii","EU-es":"chupiyá","US-es":"chupiyá","EU-fr":"puic puic","US-fr":"puic puic","EU-it":"cocoricò","EU-nl":"tjiep tjiep","CN-zh":"山雀","TW-zh":"山雀","JP-ja":"けどー","KR-ko":"허나","EU-ru":"чики-чик"},"description":"Piper is a peppy, bird villager from the Animal Crossing series. Her name and catchphrase allude to two different types of birds: her name is derived from the sandpiper, while her catchphrase is \"chickadee\". She was absent from Animal Crossing: Wild World and Animal Crossing: City Folk, but returns in Animal Crossing: New Leaf - Welcome amiibo."}